aiolinebot/__init__.py
aiolinebot/api_base.py
aiolinebot/builder.py
aiolinebot/http_client.py
aiolinebot-0.4.1.dist-info/LICENSE
aiolinebot-0.4.1.dist-info/METADATA
aiolinebot-0.4.1.dist-info/WHEEL
aiolinebot-0.4.1.dist-info/top_level.txt
aiolinebot-0.4.1.dist-info/RECORD
