Metadata-Version: 2.1
Name: aiolinebot
Version: 0.4.1
Summary: AioLineBotApi provides asynchronous interface for LINE messaging API
Home-page: https://github.com/uezo/aio-linebot-api
Author: uezo
Author-email: uezo@uezo.net
Maintainer: uezo
Maintainer-email: uezo@uezo.net
License: Apache v2
Platform: UNKNOWN
Classifier: Programming Language :: Python :: 3
Requires-Dist: line-bot-sdk
Requires-Dist: aiohttp
